{
  "extraction_timestamp": "2026-07-22T07:36:52.990052",
  "total_documents": 5,
  "documents_summary": [
    {
      "fund_name": "HDFC Large Cap Fund Direct Growth",
      "source_url": "https://groww.in/mutual-funds/hdfc-large-cap-fund-direct-growth",
      "nav": 1238.223,
      "nav_date": "21-Jul-2026",
      "aum_cr": 39023.6868,
      "expense_ratio": "1.03",
      "holdings_count": 47,
      "faq_count": 8,
      "returns": {
        "1d": 0.13,
        "1w": 0.76,
        "1m": 2.32,
        "3m": 1.64,
        "6m": -0.46,
        "1y": 0.06,
        "3y": 11.15,
        "5y": 13.52,
        "10y": 13.15,
        "since_inception": 13.26
      },
      "raw_text_length": 20534
    },
    {
      "fund_name": "HDFC Silver ETF FoF Direct Growth",
      "source_url": "https://groww.in/mutual-funds/hdfc-silver-etf-fof-direct-growth",
      "nav": 36.672,
      "nav_date": "21-Jul-2026",
      "aum_cr": 4326.5606,
      "expense_ratio": "0.22",
      "holdings_count": 3,
      "faq_count": 8,
      "returns": {
        "1d": 1.96,
        "1w": 2.06,
        "1m": -4.07,
        "3m": -10.62,
        "6m": -31.78,
        "1y": 92.16,
        "3y": 41.89,
        "since_inception": 41.99
      },
      "raw_text_length": 18987
    },
    {
      "fund_name": "HDFC Mid Cap Fund Direct Growth",
      "source_url": "https://groww.in/mutual-funds/hdfc-mid-cap-fund-direct-growth",
      "nav": 230.924,
      "nav_date": "21-Jul-2026",
      "aum_cr": 100858.3136,
      "expense_ratio": "0.75",
      "holdings_count": 78,
      "faq_count": 8,
      "returns": {
        "1d": 0.58,
        "1w": 0.4,
        "1m": 1.95,
        "3m": 4.29,
        "6m": 5.88,
        "1y": 5.83,
        "3y": 20.21,
        "5y": 20.83,
        "10y": 18.4,
        "since_inception": 20.32
      },
      "raw_text_length": 21806
    },
    {
      "fund_name": "HDFC Small Cap Fund Direct Growth",
      "source_url": "https://groww.in/mutual-funds/hdfc-small-cap-fund-direct-growth",
      "nav": 161.077,
      "nav_date": "21-Jul-2026",
      "aum_cr": 40416.8045,
      "expense_ratio": "0.76",
      "holdings_count": 85,
      "faq_count": 8,
      "returns": {
        "1d": 0.14,
        "1w": 0.92,
        "1m": 1.59,
        "3m": 5.64,
        "6m": 8.25,
        "1y": -1.29,
        "3y": 13.6,
        "5y": 16.48,
        "10y": 18.39,
        "since_inception": 18.62
      },
      "raw_text_length": 22552
    },
    {
      "fund_name": "HDFC Gold ETF Fund of Fund Direct Plan Growth",
      "source_url": "https://groww.in/mutual-funds/hdfc-gold-etf-fund-of-fund-direct-plan-growth",
      "nav": 44.4267,
      "nav_date": "21-Jul-2026",
      "aum_cr": 11019.4542,
      "expense_ratio": "0.2",
      "holdings_count": 3,
      "faq_count": 8,
      "returns": {
        "1d": 0.76,
        "1w": 1.49,
        "1m": -1.7,
        "3m": -5.94,
        "6m": -12.86,
        "1y": 43.38,
        "3y": 32.43,
        "5y": 23.05,
        "10y": 15.55,
        "since_inception": 10.8
      },
      "raw_text_length": 19166
    }
  ]
}